archetypewsgi/__init__.py
archetypewsgi/api_request_thread.py
archetypewsgi/api_requestor.py
archetypewsgi/auth_requestor.py
archetypewsgi/enums.py
archetypewsgi/fastapi.py
archetypewsgi/utils.py
archetypewsgi/api_resources/__init__.py
archetypewsgi/api_resources/api.py
archetypewsgi/api_resources/api_resource.py
archetypewsgi/api_resources/auth.py
archetypewsgi/api_resources/billable_metric.py
archetypewsgi/api_resources/client_ip.py
archetypewsgi/api_resources/customer.py
archetypewsgi/api_resources/endpoint.py
archetypewsgi/api_resources/error.py
archetypewsgi/api_resources/product.py
archetypewsgi/api_resources/track.py
archetypewsgi-1.0.6.dist-info/LICENSE
archetypewsgi-1.0.6.dist-info/METADATA
archetypewsgi-1.0.6.dist-info/WHEEL
archetypewsgi-1.0.6.dist-info/top_level.txt
archetypewsgi-1.0.6.dist-info/RECORD
