Metadata-Version: 2.1
Name: archetypewsgi
Version: 1.0.6
Summary: Python WSGI implementation for Archetype. Archetype provides packages that automatically handles API user auth and an SDK for managing your APIs.
Home-page: https://github.com/ArchetypeAPI/wsgi_sdk
Author: Archetype Team
Author-email: dev@archetype.dev
Classifier: Programming Language :: Python :: 3
Classifier: Operating System :: OS Independent
Requires-Python: >=3.6
License-File: LICENSE
Requires-Dist: requests
Requires-Dist: Flask
